senpi/__init__.py
senpi/constants.py
senpi-0.1.3.dist-info/METADATA
senpi-0.1.3.dist-info/WHEEL
senpi-0.1.3.dist-info/top_level.txt
senpi-0.1.3.dist-info/RECORD
