Metadata-Version: 2.1
Name: senpi
Version: 0.1.3
Summary: Library to facilitate the processing of and deep learning with event-based computer vision data.
Home-page: https://senpi.readthedocs.io/
Author: Adrish Kar
Author-email: example@email.com
License: MIT
Classifier: Intended Audience :: Developers
Classifier: License :: OSI Approved :: MIT License
Classifier: Programming Language :: Python
Classifier: Programming Language :: Python :: 3
Classifier: Programming Language :: Python :: 3.6
Classifier: Programming Language :: Python :: 3.7
Classifier: Programming Language :: Python :: 3.8
Classifier: Programming Language :: Python :: 3.9
Classifier: Operating System :: OS Independent
Requires-Dist: kornia
Requires-Dist: matplotlib
Requires-Dist: numpy
Requires-Dist: opencv-python
Requires-Dist: pandas
Requires-Dist: Pillow
Requires-Dist: seaborn
Requires-Dist: torch
Requires-Dist: tqdm
